neuro_api_tony/__init__.py
neuro_api_tony/__main__.py
neuro_api_tony/api.py
neuro_api_tony/cli.py
neuro_api_tony/config.py
neuro_api_tony/constants.py
neuro_api_tony/controller.py
neuro_api_tony/model.py
neuro_api_tony/py.typed
neuro_api_tony/view.py
neuro_api_tony-2.1.0.dist-info/licenses/LICENSE
neuro_api_tony-2.1.0.dist-info/METADATA
neuro_api_tony-2.1.0.dist-info/WHEEL
neuro_api_tony-2.1.0.dist-info/entry_points.txt
neuro_api_tony-2.1.0.dist-info/top_level.txt
neuro_api_tony-2.1.0.dist-info/RECORD
