Metadata-Version: 2.4
Name: neuro-api-tony
Version: 2.1.0
Summary: Graphical implementation of the Neuro API in Python
Author-email: Pasu4 <pascalwieckhorst02@gmail.com>
License: MIT License
Project-URL: Source, https://github.com/Pasu4/neuro-api-tony
Project-URL: Bug Tracker, https://github.com/Pasu4/neuro-api-tony/issues
Keywords: ai,neuro-sama,integration
Classifier: Development Status :: 4 - Beta
Classifier: Intended Audience :: Developers
Classifier: License :: OSI Approved :: MIT License
Classifier: Natural Language :: English
Classifier: Programming Language :: Python :: 3
Classifier: Programming Language :: Python :: 3.10
Classifier: Programming Language :: Python :: 3.11
Classifier: Programming Language :: Python :: 3.12
Classifier: Programming Language :: Python :: 3.13
Classifier: Programming Language :: Python :: 3.14
Classifier: Programming Language :: Python :: 3 :: Only
Classifier: Topic :: Games/Entertainment
Classifier: Topic :: Games/Entertainment :: Turn Based Strategy
Classifier: Topic :: Internet
Classifier: Topic :: Software Development :: Testing
Classifier: Topic :: Software Development :: Testing :: Mocking
Classifier: Operating System :: OS Independent
Classifier: Typing :: Typed
Requires-Python: >=3.10
License-File: LICENSE
Requires-Dist: attrs~=25.3.0
Requires-Dist: dataclass-wizard==0.36.2
Requires-Dist: Faker~=37.5.3
Requires-Dist: jsf~=0.11.2
Requires-Dist: json-source-map~=1.0.5
Requires-Dist: jsonschema~=4.25.0
Requires-Dist: neuro-api~=3.1.1
Requires-Dist: outcome~=1.3.0.post0
Requires-Dist: requests~=2.32.4
Requires-Dist: semver~=3.0.4
Requires-Dist: trio>=0.32.0
Requires-Dist: trio-websocket~=0.12.2
Requires-Dist: wxPython~=4.2.3
Provides-Extra: tests
Requires-Dist: pytest>=8.3.4; extra == "tests"
Requires-Dist: pytest-cov>=6.0.0; extra == "tests"
Requires-Dist: pytest-trio>=0.8.0; extra == "tests"
Requires-Dist: coverage>=7.6.12; extra == "tests"
Requires-Dist: exceptiongroup>=1.2.2; extra == "tests"
Provides-Extra: tools
Requires-Dist: uv>=0.8.4; extra == "tools"
Requires-Dist: ruff>=0.12.7; extra == "tools"
Requires-Dist: codespell>=2.4.1; extra == "tools"
Requires-Dist: mypy>=1.19.0; extra == "tools"
Requires-Dist: types-requests>=2.32.0.20241016; extra == "tools"
Requires-Dist: pre-commit>=4.2.0; extra == "tools"
Dynamic: license-file
